docs/source/conf.py
examples/electrostatics/model.py
examples/electrostatics/run_gg.py
examples/electrostatics/run_pygmo_ipopt.py
examples/electrostatics/run_pygmo_nlopt.py
examples/electrostatics/run_pymoo.py
examples/mixed/model.py
examples/mixed/run.py
examples/multi_obj_chain/model.py
examples/multi_obj_chain/run_pymoo.py
iwopy/__init__.py
iwopy/benchmarks/__init__.py
iwopy/benchmarks/branin/__init__.py
iwopy/benchmarks/branin/branin.py
iwopy/benchmarks/rosenbrock/__init__.py
iwopy/benchmarks/rosenbrock/rosenbrock.py
iwopy/core/__init__.py
iwopy/core/base.py
iwopy/core/constraint.py
iwopy/core/function.py
iwopy/core/function_list.py
iwopy/core/function_subset.py
iwopy/core/memory.py
iwopy/core/objective.py
iwopy/core/opt_results.py
iwopy/core/optimizer.py
iwopy/core/problem.py
iwopy/interfaces/__init__.py
iwopy/interfaces/pygmo/__init__.py
iwopy/interfaces/pygmo/algos.py
iwopy/interfaces/pygmo/imports.py
iwopy/interfaces/pygmo/optimizer.py
iwopy/interfaces/pygmo/problem.py
iwopy/interfaces/pymoo/__init__.py
iwopy/interfaces/pymoo/factory.py
iwopy/interfaces/pymoo/imports.py
iwopy/interfaces/pymoo/optimizer.py
iwopy/interfaces/pymoo/problem.py
iwopy/interfaces/scipy/__init__.py
iwopy/interfaces/scipy/optimizer.py
iwopy/optimizers/__init__.py
iwopy/optimizers/gg.py
iwopy/utils/__init__.py
iwopy/utils/discretization.py
iwopy/utils/load.py
iwopy/utils/stdout.py
iwopy/utils/subclasses.py
iwopy/wrappers/__init__.py
iwopy/wrappers/discretize_reg_grid.py
iwopy/wrappers/local_fd.py
iwopy/wrappers/problem_wrapper.py
iwopy/wrappers/simple_constraint.py
iwopy/wrappers/simple_objective.py
iwopy/wrappers/simple_problem.py
iwopy-0.4.0.dist-info/licenses/LICENSE
tests/core/test_discr_grid.py
tests/core/test_discretize.py
tests/core/test_gradients_ana.py
tests/core/test_varmap.py
tests/pymoo/test_pymoo.py
tests/scipy/test_scipy.py
iwopy-0.4.0.dist-info/METADATA
iwopy-0.4.0.dist-info/WHEEL
iwopy-0.4.0.dist-info/top_level.txt
iwopy-0.4.0.dist-info/RECORD
