Metadata-Version: 2.4
Name: iwopy
Version: 0.4.0
Summary: Fraunhofer IWES optimization tools in Python
Author: Jonas Schulte, Bernhard Stoevesandt
Maintainer: Jonas Schulte
License: MIT License
Project-URL: Homepage, https://github.com/FraunhoferIWES/iwopy
Project-URL: Documentation, https://fraunhoferiwes.github.io/iwopy
Project-URL: Repository, https://github.com/FraunhoferIWES/iwopy.git
Project-URL: Bug Tracker, https://github.com/FraunhoferIWES/iwopy/issues
Project-URL: Changelog, https://github.com/FraunhoferIWES/iwopy/blob/main/CHANGELOG.md
Keywords: Optimization,Interface
Classifier: Topic :: Scientific/Engineering
Classifier: Intended Audience :: Developers
Classifier: Intended Audience :: Science/Research
Classifier: Programming Language :: Python :: 3
Classifier: Programming Language :: Python :: 3.9
Classifier: Programming Language :: Python :: 3.10
Classifier: Programming Language :: Python :: 3.11
Classifier: Programming Language :: Python :: 3.12
Classifier: Programming Language :: Python :: 3.13
Classifier: License :: OSI Approved :: MIT License
Classifier: Operating System :: OS Independent
Classifier: Development Status :: 4 - Beta
Requires-Python: >=3.9
License-File: LICENSE
Requires-Dist: matplotlib>=3.8
Requires-Dist: numpy>=1.26
Requires-Dist: scipy>=1.12
Provides-Extra: opt
Requires-Dist: pygmo>=0.1; extra == "opt"
Requires-Dist: pymoo>=0.6; extra == "opt"
Provides-Extra: test
Requires-Dist: pytest>=7.0; extra == "test"
Requires-Dist: nbmake>1.0; extra == "test"
Requires-Dist: pygmo>=0.1; extra == "test"
Requires-Dist: pymoo>=0.6; extra == "test"
Provides-Extra: doc
Requires-Dist: setuptools>=61.0; extra == "doc"
Requires-Dist: sphinx>=5.0; extra == "doc"
Requires-Dist: sphinx-immaterial>=0.10; extra == "doc"
Requires-Dist: myst-nb>=0.1; extra == "doc"
Requires-Dist: ipykernel>=5.0; extra == "doc"
Requires-Dist: ipywidgets>=5.0; extra == "doc"
Requires-Dist: m2r2>=0.2; extra == "doc"
Requires-Dist: lxml_html_clean>=0.4; extra == "doc"
Provides-Extra: dev
Requires-Dist: pre-commit>=0.1; extra == "dev"
Requires-Dist: objsize>=0.5; extra == "dev"
Requires-Dist: jupyter>=1.0; extra == "dev"
Dynamic: license-file
